mylib_050/__init__.py
mylib_050-0.1.dist-info/LICENSE.txt
mylib_050-0.1.dist-info/METADATA
mylib_050-0.1.dist-info/WHEEL
mylib_050-0.1.dist-info/top_level.txt
mylib_050-0.1.dist-info/RECORD
